internxt_data_tools/BigQuery.py
internxt_data_tools/Mongo.py
internxt_data_tools/Schemas.py
internxt_data_tools/StripeAdapter.py
internxt_data_tools/__init__.py
internxt_data_tools/charges_schema.py
internxt_data_tools/customer_schema.py
internxt_data_tools/invoices_schema.py
internxt_data_tools/prices_schema.py
internxt_data_tools/sessions_schema.py
internxt_data_tools/subscription_schema.py
internxt_data_tools/utils.py
internxt_data_tools-0.0.10.dist-info/LICENSE
internxt_data_tools-0.0.10.dist-info/WHEEL
internxt_data_tools-0.0.10.dist-info/METADATA
internxt_data_tools-0.0.10.dist-info/RECORD
